zask/__init__.py
zask/_compat.py
zask/config.py
zask/logging.py
zask/utils.py
zask/ext/__init__.py
zask/ext/sqlalchemy/__init__.py
zask/ext/sqlalchemy/_compat.py
zask/ext/zerorpc/__init__.py
Zask-1.9.8.dist-info/AUTHORS
Zask-1.9.8.dist-info/LICENSE
Zask-1.9.8.dist-info/METADATA
Zask-1.9.8.dist-info/WHEEL
Zask-1.9.8.dist-info/top_level.txt
Zask-1.9.8.dist-info/RECORD
